[
    {
        "name": "Bryan",
        "score": 540,
        "ai_defeated": "item_focused",
        "date": "2025-05-23 21:39"
    },
    {
        "name": "Jumbo",
        "score": 480,
        "ai_defeated": "item_focused",
        "date": "2025-06-08 02:45"
    },
    {
        "name": "Ben",
        "score": 360,
        "ai_defeated": "conservative",
        "date": "2025-06-08 21:49"
    },
    {
        "name": "Chxyuuu",
        "score": 320,
        "ai_defeated": "item_focused",
        "date": "2025-05-23 21:56"
    },
    {
        "name": "Benson",
        "score": 170,
        "ai_defeated": "conservative",
        "date": "2025-06-08 23:58"
    },
    {
        "name": "Player",
        "score": 140,
        "ai_defeated": "conservative",
        "date": "2025-06-08 23:34"
    },
    {
        "name": "bryan",
        "score": 140,
        "ai_defeated": "item_focused",
        "date": "2025-06-08 23:51"
    },
    {
        "name": "Victory",
        "score": 120,
        "ai_defeated": "conservative",
        "date": "2025-06-08 23:47"
    }
]